setup.cfg
setup.py
quantumworldX/__init__.py
quantumworldX/core.py
quantumworldX/helium.py
quantumworldX/hydrogen.py
quantumworldX/plot.py
quantumworldX.egg-info/PKG-INFO
quantumworldX.egg-info/SOURCES.txt
quantumworldX.egg-info/dependency_links.txt
quantumworldX.egg-info/requires.txt
quantumworldX.egg-info/top_level.txt