Metadata-Version: 1.0
Name: quantumworldX
Version: 0.18.44
Summary: Basic library for the QuantumWorld edX course
Home-page: https://pythonhosted.org/quantumworldX/
Author: Benjamin Sanchez Lengeling
Author-email: beangoben@gmail.com
License: MIT
Keywords: Quantum Chemistry,edX,Quantum Mechanics
Platform: UNKNOWN
